mlimputer/__init__.py
mlimputer/imputation.py
mlimputer/core/__init__.py
mlimputer/core/abstract.py
mlimputer/core/base.py
mlimputer/core/strategy_mapper.py
mlimputer/data/__init__.py
mlimputer/data/base_generator.py
mlimputer/data/data_generator.py
mlimputer/evaluation/__init__.py
mlimputer/evaluation/abstract.py
mlimputer/evaluation/cross_validation.py
mlimputer/evaluation/evaluator.py
mlimputer/evaluation/metrics.py
mlimputer/models/__init__.py
mlimputer/models/boosting.py
mlimputer/models/neighbors.py
mlimputer/models/tree_based.py
mlimputer/pipeline/__init__.py
mlimputer/pipeline/base.py
mlimputer/pipeline/builder.py
mlimputer/pipeline/factory.py
mlimputer/preprocessing/__init__.py
mlimputer/preprocessing/abstract.py
mlimputer/preprocessing/encoders.py
mlimputer/preprocessing/imputers.py
mlimputer/schemas/__init__.py
mlimputer/schemas/config.py
mlimputer/schemas/parameters.py
mlimputer/utils/__init__.py
mlimputer/utils/constants.py
mlimputer/utils/exceptions.py
mlimputer/utils/logging.py
mlimputer/utils/serialization.py
mlimputer/utils/splitter.py
mlimputer-2.0.24.dist-info/licenses/LICENSE
mlimputer-2.0.24.dist-info/METADATA
mlimputer-2.0.24.dist-info/WHEEL
mlimputer-2.0.24.dist-info/top_level.txt
mlimputer-2.0.24.dist-info/RECORD
