Metadata-Version: 2.4
Name: mlimputer
Version: 2.0.24
Summary: MLimputer - Missing Data Imputation Framework for Machine Learning
Home-page: https://github.com/TsLu1s/MLimputer
Author: Luís Fernando da Silva Santos
Author-email: luisf_ssantos@hotmail.com
License: MIT
Keywords: machine learning,missing data imputation,data preprocessing,supervised learning,predictive imputation,multivariate imputation,random forest imputation,gradient boosting imputation,knn imputation,automated imputation,missing values,data science,ml pipeline
Classifier: Intended Audience :: Education
Classifier: Intended Audience :: Developers
Classifier: Intended Audience :: Science/Research
Classifier: Intended Audience :: Customer Service
Classifier: Intended Audience :: Financial and Insurance Industry
Classifier: Intended Audience :: Healthcare Industry
Classifier: Intended Audience :: Telecommunications Industry
Classifier: Topic :: Scientific/Engineering :: Artificial Intelligence
Classifier: Topic :: Scientific/Engineering :: Information Analysis
Classifier: License :: OSI Approved :: MIT License
Classifier: Operating System :: OS Independent
Classifier: Programming Language :: Python :: 3.10
Classifier: Programming Language :: Python :: 3.11
Classifier: Programming Language :: Python :: 3.12
License-File: LICENSE
Requires-Dist: numpy>=1.20.0
Requires-Dist: pandas>=1.3.0
Requires-Dist: scikit-learn>=1.0.0
Requires-Dist: pydantic>=2.0.0
Requires-Dist: catboost>=1.1.1
Requires-Dist: xgboost==2.0.3
Requires-Dist: joblib>=1.0.0
Requires-Dist: tqdm>=4.62.0
Dynamic: author
Dynamic: author-email
Dynamic: classifier
Dynamic: description
Dynamic: description-content-type
Dynamic: home-page
Dynamic: keywords
Dynamic: license
Dynamic: license-file
Dynamic: requires-dist
Dynamic: summary
